{
    "recipes": [
{
    "id": 1,
    "name": "Baked Mutton Leg",
    "category": "Main Courses - Lamb",
    "ingredients": [
      "Mutton leg 1 (2 kg weight)",
      "Papaya paste 4 tbsp",
      "Lemon juice 2 tbsp",
      "Ginger garlic paste 2 tbsp",
      "Green chilies 4 (chopped)",
      "Red chili powder 1 tbsp",
      "Black pepper 1 tbsp (crushed)",
      "Garam masala powder 1 tsp",
      "Salt to taste",
      "Oil 4 tbsp",
      "Onion 2 medium (sliced)",
      "Tomato 2 (sliced)",
      "Capsicum 2 (sliced)",
      "Aluminium foil"
    ],
    "instructions": [
      "Debone mutton leg and beat with hammer. Apply papaya paste and leave for 1 hour.",
      "In a bowl combine lemon juice, ginger garlic paste, green chilies, red chili, black pepper, garam masala, salt and oil.",
      "Coat mutton leg with this marination and leave for 4-6 hours.",
      "Then put mutton leg on aluminium foil, top with onion, tomato, and capsicum and wrap carefully.",
      "Bake in preheated oven at 180 C for 40-50 minutes or until fully tender.",
      "Set in serving platter garnish with lemon wedges and sliced onion and serve"
    ]
  },
  {
    "id": 2,
    "name": "Siri Paye",
    "category": "Main Courses - Lamb",
    "ingredients": [
      "Skull with Brain 1",
      "Goat Feet 6",
      "Ginger Garlic Paste 2tbsp",
      "Onion 2 (sliced)",
      "Oil 1 cup",
      "Bay Leaves 1-2",
      "Cloves 5-6",
      "Green Cardamom 4-5",
      "Yogurt 1 cup",
      "Coriander Powder 2 tbsp",
      "Garam masala Powder (with nutmeg and mace) 1tbsp",
      "Red Chili Powder 3 tbsp",
      "Turmeric Powder 1 tbsp",
      "Salt to taste",
      "Cumin Powder 1 tbsp",
      "Fried onion for garnish",
      "Green chilies for Garnish",
      "Fresh Coriander for garnish",
      "Lemon for garnish",
      "Whole Ginger for garnish",
      "Garam masala powder for garnish"
    ],
    "instructions": [
      "Separate the brain from the skull. In a pot pour 2 cups of water and add 1/2tsp of turmeric and boil it.",
      "Then add brain to it and boil for 4 to 5 mins. Then strain it and put aside.",
      "Now in a pot put the skull and feet and add 1tbsp of Ginger garlic paste, onion; stir fry 4-5 minutes then add sufficient amount of water and cook for 4-5 hours.",
      "Take another pan, pour oil to heat, add bay leaves, cloves and green cardamoms; stir fry it.",
      "Now add 1 tbsp ginger garlic paste, yogurt, coriander powder, garam masala powder, red chili powder, turmeric powder, cumin powder and salt to taste and stir fry it.",
      "When masala is ready add the skull and feet to it along gravy and cook on low flame. Set consistency of gravy according to desire. Sprinkle Garam masala powder add brain and at the end.",
      "Now serve with fried onions, green chilies, ginger, fresh coriander, lemons."
    ]
  },
  {
    "id": 3,
    "name": "Noor Jehani Qorma",
    "category": "Main Courses - Lamb",
    "ingredients": [
      "Mutton ½ kg",
      "Almonds 125 gm",
      "Clarified butter 125 gm",
      "Onion yogurt 125 gm",
      "Garlic 1 bulb",
      "Coriander powder 2 tbsp",
      "Red chili powder 2 tsp",
      "Salt to taste",
      "Ginger garlic paste 3 tbsp",
      "Whole all spices 20 gm"
    ],
    "instructions": [
      "Blanch almonds and keep a side.",
      "Fry onion until brown and take out, crush and keep a side.",
      "Add ginger garlic paste and other spices and fry.",
      "Now add yogurt and meat fry well.",
      "Now add fried and crushed onion and almond with little water, cook on lower flame to allow meat tender well.",
      "When meat tenderized, fry for a while then remove.",
      "Noor jehani qorma is ready to enjoy with naan."
    ]
  },
  {
    "id": 4,
    "name": "Gosht Saag Wala",
    "category": "Main Courses - Lamb",
    "ingredients": [
      "Mutton ½ kg",
      "Spinach ½ kg",
      "Green chilies 6",
      "Tomato 1",
      "Fenugreek leaves 2 small bunches",
      "Oil ½ cup",
      "Onion ½ cup (brown)",
      "Ginger garlic paste 1 tbsp",
      "Chili powder 1 tbsp",
      "Turmeric ¼ tsp",
      "Salt 1 tsp",
      "Coriander powder 1 ½ tsp",
      "Yogurt 1 cup",
      "Milk ½ cup",
      "Fenugreek 2 tsp (dried)"
    ],
    "instructions": [
      "Clean, wash, boil and blend spinach with green chilies, tomatoes and fenugreek leaves, keep aside.",
      "Heat oil add brown onion, ginger garlic paste with all the seasonings and mutton, fry for 10 minutes.",
      "Add in yogurt, fry well.",
      "Add 1 ½ cup water, cover and cook till mutton nearly done.",
      "Add in your blended spinach mixture cover and cook again till oil comes on top.",
      "Lastly add milk and dried fenugreek, fry and remove."
    ]
  },
  {
    "id": 5,
    "name": "Mirchi Keema",
    "category": "Main Courses - Lamb",
    "ingredients": [
      "Mince ½ kg",
      "Capsicum 2",
      "Oil ½ cup",
      "Onion 2 cup (sliced)",
      "Ginger garlic paste 1 tbsp heaped",
      "Salt 1 tsp heaped",
      "Chili powder 1 tbsp",
      "Turmeric ¼ tsp",
      "Coriander powder 1 tbsp",
      "Cumin powder 1 tsp",
      "Tomatoes 3",
      "Garam masala powder 1 tsp",
      "Green chilies 6",
      "Coriander leaves few",
      "Lemon juice ¼ cup"
    ],
    "instructions": [
      "Heat oil fry onion until soft remove half of the fried onion and keep aside.",
      "Allow remaining onion to fry until golden.",
      "Add ginger garlic paste, salt, chili powder, turmeric, coriander and cumin.",
      "Add mince, fry well until oil comes out.",
      "Remove half the mince and keep aside.",
      "Cut capsicum and tomatoes in 1 inch pieces and keep aside.",
      "Put the tomatoes on the mince on the pan.",
      "Cover with remaining onion which we took out.",
      "Add capsicum on top of onion, cover with remaining mince.",
      "Add Garam masala powder over the mince, green chilies, coriander leaves and lemon juice.",
      "Cover with lid and cook on low flame.",
      "Simmer once and remove, serve with roti."
    ]
  },
  {
    "id": 6,
    "name": "Special Korma",
    "category": "Main Courses - Lamb",
    "ingredients": [
      "Mutton ½ kg",
      "Yogurt 1 cup",
      "Coconut 1 tbsp (desiccated)",
      "Almonds 10",
      "Poppy seeds 1 tsp",
      "Ginger garlic paste 1 tbsp",
      "Coriander powder 1 ½ tsp",
      "Chili powder 2 tsp",
      "Garam masala powder 1 tsp",
      "Turmeric ¼ tsp",
      "Oil ½ cup",
      "Cinnamon stick 1",
      "Green cardamom 4",
      "Brown onion 4 tbsp (grinded)",
      "Coriander leaves 2 tbsp",
      "Mint leaves 10 – 12",
      "Green chilies 4 (whole)",
      "Saffron ¼ tsp"
    ],
    "instructions": [
      "Beat yogurt, mix with coconut, almonds, poppy seed, saffron, ginger garlic paste, coriander powder, chili powder, Garam masala powder and turmeric.",
      "Heat oil add cinnamon, green cardamom and mutton, fry well.",
      "Add in yogurt mixture and fry well.",
      "Add 2 cup water, cover and cook till meat tender.",
      "Then add brown onion, coriander leaves, green chilies, mint leaves and saffron.",
      "When oil comes on top, remove and serve."
    ]
  },
  {
    "id": 7,
    "name": "Darbari Brain Masala",
    "category": "Main Courses - Lamb",
    "ingredients": [
      "Mutton brain 3",
      "Oil ½ cup",
      "Onion 1 cup (chopped)",
      "Ginger garlic paste 1 tbsp",
      "Salt 1 tsp",
      "Chili powder 1 ½ tsp",
      "Tomato 2 (chopped)",
      "Yogurt ½ cup",
      "Fresh cream 1 tbsp",
      "Garam masala powder ½ tsp",
      "Green chilies 4 (chopped)",
      "Coriander leaves 3 tbsp (chopped)",
      "Ginger 1 tbsp (slice)"
    ],
    "instructions": [
      "Wash and remove veins from brain.",
      "Heat oil in a wok, fry chopped onion till light golden.",
      "Add ginger garlic paste, salt, chili powder, tomatoes and yogurt, fry well till oil comes on top.",
      "Add brain, cover and cook for 10 minutes.",
      "Lastly add cream, garam masala powder, coriander, green chilies and ginger.",
      "Serve with nan."
    ]
  },
  {
    "id": 8,
    "name": "Bengali Mutton Curry",
    "category": "Main Courses - Lamb",
    "ingredients": [
      "Mutton ½ kg",
      "Potatoes 4 (boiled)",
      "Mustard oil 1 cup",
      "Onion 3 (chopped)",
      "Salt to taste",
      "Turmeric 1 tsp",
      "Ginger garlic paste 1 tbsp",
      "Fresh red chilies 8 (chopped)",
      "Coriander seeds 1 tbsp",
      "Cinnamon 1 tsp (roasted and crushed)",
      "Black pepper 1 tsp (crushed)",
      "Bay leave 1",
      "Green chilies 4",
      "Lemons 3"
    ],
    "instructions": [
      "Cut potatoes into cubes and fry them till golden brown.",
      "Add in mustard oil in the pan and add in onion.",
      "Fry them till they are golden brown.",
      "Add in mutton, salt, turmeric and ginger garlic paste and cook it.",
      "When the water of the meat dries, add in red chilies, coriander seeds, cinnamon, black pepper and a bay leave.",
      "Sauté it and when the meat tenders add in fried potatoes, green chilies and lemon juice.",
      "Simmer it and serve Bengali Mutton curry with plain rice."
    ]
  },
  {
    "id": 9,
    "name": "Gulabi Mutton",
    "category": "Main Courses - Lamb",
    "ingredients": [
      "Mutton ½ kg",
      "Oil 4 – 5 tbsp",
      "Onion 1 medium",
      "Ginger garlic paste 2 tbsp",
      "Cloves 4 – 5",
      "Green cardamom 5 – 6",
      "Tomato paste 4 tbsp",
      "Yogurt 125 gm",
      "Garam masala powder ½ tsp",
      "Chili powder 1 tbsp",
      "Salt to taste",
      "Water 1 cup",
      "Almond 25 gm (chopped)",
      "Coriander leaves ¼ bunch (chopped)",
      "Ginger 1 piece"
    ],
    "instructions": [
      "Heat 4 – 5 tbsp oil in a wok, add in onion and sauté till golden brown.",
      "Then add ginger garlic paste and mutton.",
      "Fry well till its color is changed and water dries.",
      "Add cloves, green cardamoms, tomato paste and yogurt.",
      "Mix well and cook for 1 – 2 minutes.",
      "Then add Garam masala powder, chili powder, salt and water as required.",
      "Cover and cook for 25 – 30 minutes till meat is tender.",
      "Lastly add almond and coriander leaves.",
      "Dish it out garnish with ginger and serve hot."
    ]
  },
  {
    "id": 10,
    "name": "Raan Dum Pukht",
    "category": "Main Courses - Lamb",
    "ingredients": [
      "Mutton leg 1 whole",
      "Salt to taste",
      "Lemon (juice) 2 lemons",
      "Papaya paste 2 tbsp",
      "Butter 5 tbsp",
      "Oil 3 tbsp",
      "Onion 2 – 3",
      "Ginger garlic paste 2 tbsp",
      "Vinegar 5 tbsp",
      "Cumin powder 1 tbsp",
      "Turmeric 1 tsp",
      "Chili powder 1 tbsp",
      "Coriander powder 1 tbsp",
      "Garam masala powder 1 tsp",
      "Coriander leaves ½ bunch",
      "Mint leaves ¼ bunch",
      "Ginger 1 medium piece",
      "Green chilies 2 – 3",
      "Chaat masala 1 tbsp"
    ],
    "instructions": [
      "Mark cuts on whole mutton leg, marinate with a little salt, lemon juice and papaya paste.",
      "In another pan heat butter and oil.",
      "Add in onion and sauté till softened.",
      "Then add mutton leg, fry well till its color is changed.",
      "Add ginger garlic paste, vinegar, cumin seeds, turmeric, chili powder, coriander powder and garam masala powder.",
      "Fry well for 1 – 2 minutes, now add 1 glass of water, cover and cook for 25 – 30 minutes.",
      "Now remove lid, add coriander leaves, mint leaves, green chilies and ginger. Mix well.",
      "Now remove mixture in a serving platter.",
      "Sprinkle with chaat masala and serve hot."
    ]
  },
  {
    "id": 11,
    "name": "Mutton Steam",
    "category": "Main Courses - Lamb",
    "ingredients": [
      "Mutton 1 kg",
      "Salt to taste",
      "Vinegar 2 cup",
      "Ginger garlic paste 2 tbsp",
      "Chili powder 2 tbsp",
      "Garam masala powder 1 tbsp",
      "Cumin powder 1 tbsp",
      "Nutmeg ½ tsp (ground)",
      "Yogurt 375 gm",
      "Chaat masala 2 tbsp",
      "Oil for frying"
    ],
    "instructions": [
      "Marinate mutton with salt, vinegar and ginger garlic paste. Mix well.",
      "In a bowl add chili powder, garam masala powder, cumin powder, nutmeg, yogurt and chaat masala. Mix well.",
      "Then fry the marinated mince till golden brown.",
      "Again coat the mutton pieces with yogurt mixture.",
      "Then cook in steamer till tender.",
      "Dish it out and serve hot."
    ]
  },
  {
    "id": 12,
    "name": "Lagan Kay Kofty",
    "category": "Main Courses - Lamb",
    "ingredients": [
      "Mince ½ kg",
      "Onion 2 (sliced)",
      "Green chili 4 (chopped)",
      "Oil ½ cup",
      "Yogurt ½ cup",
      "Salt 1 tsp",
      "Ginger garlic paste 1 tsp",
      "Red chili powder 1 tsp",
      "Garam masala powder 1 tsp",
      "Roasted gram 3 tsp (heaped)",
      "Raw papaya ½ tsp",
      "Brown onion 2 tbsp (grinded)",
      "Coriander leaves 2 tbsp (chopped)"
    ],
    "instructions": [
      "Marinate mince with salt and papaya for 15 minutes.",
      "Then add to ginger garlic paste, chili powder, brown onion, chopped coriander, chopped green chilies, garam masala powder and ground roasted gram.",
      "Mix everything well, make into round balls, spread in a greased lagan.",
      "Cook for 5 minutes, then add in oil, in another pan.",
      "Sauté onion till light brown, add in it yogurt.",
      "Fry for 5 minutes, remove, pour this over to kofta and serve immediately."
    ]
  },
  {
    "id": 13,
    "name": "IlahaBadi Champ",
    "category": "Main Courses - Lamb",
    "ingredients": [
      "Mutton chops ½ kg",
      "Oil for fry",
      "Ginger garlic paste 2 tbsp",
      "Nutmeg mace powder ½ tsp",
      "Salt to taste",
      "Black pepper powder ½ tsp",
      "Cinnamon powder ½ tsp",
      "Chili powder 1 tsp",
      "Turmeric ½ tsp",
      "Yogurt 125 gm",
      "Cumin seeds 1 tsp (ground)",
      "Flour ½ cup",
      "Egg 2 (beaten)",
      "Sesame seeds 1 tbsp",
      "Lemon juice little",
      "Onion 1"
    ],
    "instructions": [
      "Beat mutton chops with steak hammer.",
      "In a wok heat 2 – 3 tbsp oil, add ginger garlic paste and mutton chops.",
      "Fry fro 2 – 3 minutes.",
      "Now add nutmeg mace powder, salt, black pepper powder, cinnamon powder, chili powder, turmeric, yogurt and cumin seeds. Mix well.",
      "Now add 1 cup water, cover and cook for 20 – 25 minutes till chops are tender.",
      "Now remove chops from pan, coat with ½ cup flour.",
      "Dip in beaten egg. Sprinkle with 1 tbsp sesame seeds.",
      "Now deep fry till golden brown.",
      "Remove from oil.",
      "Serve with lemon juice and onion"
    ]
  },
  {
    "id": 14,
    "name": "Bhopali Korma",
    "category": "Main Courses - Lamb",
    "ingredients": [
      "Mutton meat ½ kg",
      "Whole coriander 1 tbsp",
      "Cumin seeds 1 tbsp (crushed)",
      "Muslin cloth as required",
      "Oil ¼ cup",
      "Onion 2 (medium sized, finely sliced)",
      "Ginger garlic paste 2 tbsp",
      "Yogurt 125 gm",
      "Red chili powder 1 tbsp",
      "Turmeric 1 tsp",
      "All spice powder 1 tsp",
      "Cardamom powder ½ tsp",
      "Fennel seeds 1 tbsp",
      "Salt as required",
      "Nutmeg and mace powder ½ tsp",
      "Green chilies 3-4",
      "Coriander powder 2 tbsp"
    ],
    "instructions": [
      "In a muslin cloth place the whole coriander and cumin then wrap it.",
      "Heat oil in a pan and fry the finely sliced onion and ginger garlic paste for a few minutes.",
      "Add in mutton and the spice bag.",
      "Fry the mutton until the onions are uniformly distributed.",
      "Add the yogurt, coriander powder, red chili powder, turmeric, all spice powder, cardamom powder, fennel seeds, salt, nutmeg and mace powder.",
      "Add 1 cup water, cover and simmer for 15-20 minutes or until the meat is tender.",
      "Now add the green chilies and increase the flame.",
      "Cook until the gravy thickens.",
      "The bhopali korma is now ready to serve."
    ]
  },
  {
    "id": 15,
    "name": "Balochi Bhindi Gosht",
    "category": "Main Courses - Lamb",
    "ingredients": [
      "Mutton ½ kg",
      "Ladyfinger ½ kg",
      "Oil for deep frying",
      "Onion 3",
      "Ginger 1 piece",
      "Garlic cloves 6 – 7",
      "Oil ¼ cup",
      "Whole spices as required",
      "Turmeric 1 tsp",
      "Chili powder 1 tbsp",
      "Coriander powder 1 tbsp",
      "Salt to taste",
      "Yogurt 125 gm (whipped)",
      "Garam masala powder 1tsp"
    ],
    "instructions": [
      "Remove top and bottom of ladyfingers.",
      "Deep fry in oil till golden brown, remove and keep aside.",
      "In blender put together onion, ginger, garlic clove and 1 cup water. Blend finely to a paste.",
      "Heat oil in pan, add mix whole spice and ginger garlic paste. Fry for 4 – 5 minutes.",
      "Now add turmeric powder, chili powder, coriander powder and mutton.",
      "Also add 1 cup water, cover and cook for 20 – 25 minutes.",
      "Add salt, yogurt and fried ladyfingers.",
      "Mix well and simmer for 4 – 5 minutes till oil comes on top.",
      "Lastly sprinkle garam masala powder and serve hot."
    ]
  },
  {
    "id": 16,
    "name": "Mutton Turnip Curry",
    "category": "Main Courses - Lamb",
    "ingredients": [
      "Mutton ½ kg",
      "Red chili 1 ½ tsp",
      "Fresh coriander ½ bunch",
      "Garam masala powder ½ tsp",
      "Garlic 1 tsp",
      "Clarified butter ½ cup",
      "Green chili 4",
      "Salt 1 tsp",
      "Turnip 1 tsp",
      "Tomato 1 medium",
      "Ginger 1 tsp",
      "Turmeric ½ tsp",
      "Onion 2 medium"
    ],
    "instructions": [
      "Add onion and tomatoes in blender with half cup water and blend well.",
      "Peel turnips and boil them.",
      "Heat clarified butter and add onion mixture, ginger, garlic, salt, red chili, turmeric and roast well.",
      "When clarified butter becomes up then add meat and cook for a while.",
      "Then add two cups water and cook more.",
      "When meat tenderized then combine boiled turnips and one cup water and cook for 10 minutes.",
      "Finally add garam masala powder, fresh coriander and green chilies and turn off stove.",
      "Serve with boiled rice, salad or bread."
    ]
  },
  {
    "id": 17,
    "name": "Mutton Aloo Bukhara",
    "category": "Main Courses - Lamb",
    "ingredients": [
      "Mutton ½ kg",
      "Oil ¼ cup",
      "Ginger garlic paste 2 tbsp",
      "Red chili powder 1 tbsp",
      "Salt to taste",
      "Turmeric ½ tsp",
      "Dry plum 250 gm",
      "Black pepper 1 tsp (crushed)",
      "Garam masala powder ½ tsp",
      "Tomatoes 3 (chopperized)"
    ],
    "instructions": [
      "In a pan heat oil, add ginger garlic paste and mutton.",
      "Fry well till its color turn to golden brown.",
      "Now add red chili powder, salt, turmeric and water as required.",
      "Cover and cook on low flame for 20 – 25 minutes.",
      "Now remove lid, add dry plum, black pepper, garam masala powder and tomatoes.",
      "Fry well on high flame till water dries.",
      "Dish it out and serve hot."
    ]
  },
  {
    "id": 18,
    "name": "Dahi Kashmiri Gosht",
    "category": "Main Courses - Lamb",
    "ingredients": [
      "Undercut 1 kg",
      "Oil 1 cup",
      "Onion 3 (chopped)",
      "Yogurt 1 cup",
      "Whole red chilies 8 (chopped)",
      "Ginger garlic 1 tbsp (chopped)",
      "White cumin seeds 1 tsp",
      "Coriander seeds 1 tbsp",
      "Black pepper 1 tsp",
      "Green chili 4",
      "Salt to taste",
      "Butter ½ tbsp",
      "Onion 1",
      "Ginger 1 inch piece",
      "Garlic 1",
      "Cinnamon stick 1",
      "Coriander seeds 1 tsp",
      "Salt to taste"
    ],
    "instructions": [
      "Take 3 cup water in a wok along with undercut, onion, ginger, garlic, cinnamon stick, coriander seeds and salt to make stock.",
      "Boil it and after 5-10 minutes take out the meat and drain the stock.",
      "Now take 1 cup oil in a wok and fry chopped onions till golden brown.",
      "Take them out in a tissue paper make it dry and crisp.",
      "Now add the meat in that oil.",
      "Blend yogurt and onion together in a blender.",
      "When the water in the meat dries add in the blended mixture and add red chilies, ginger garlic, white cumin seeds, coriander seeds, black pepper and green chilies.",
      "Then add in some salt and stock.",
      "Cook it on a low flame.",
      "Add butter when the oil separates and cook it for 10 minutes on a low flame.",
      "Serve Dahi Kashmiri Gosht with nan."
    ]
  },
  {
    "id": 19,
    "name": "Jahangiri Korma",
    "category": "Main Courses - Lamb",
    "ingredients": [
      "Mutton 1 kg",
      "Ginger Garlic 1 tbsp",
      "Red chili powder 1 tbsp",
      "Cumin seeds 1 tsp",
      "Salt to taste",
      "Oil 1 cup",
      "Onion 1",
      "Yogurt 1 cup",
      "Dry coriander powder 1 tsp",
      "Turmeric ½ tsp",
      "Black pepper 10",
      "Coriander leaves 1 bunch",
      "Almonds 10"
    ],
    "instructions": [
      "Take half of the yogurt and mix in dry coriander, black pepper, turmeric, salt, red chili powder, cumin, ginger and garlic.",
      "Now add yogurt mixture to meat and set aside for 15 to 20 minutes.",
      "Now heat oil in a pan, add onions and fry till golden.",
      "Now add in meat and cook for a while.",
      "When meat is cooked and water reduces.",
      "Add the remaining yogurt, cover and cook for five minutes on low flame.",
      "When oil starts to separate and rich aroma is erupting from the pan, turn off the flame.",
      "Garnish with chopped fresh coriander and almonds."
    ]
  },
  {
    "id": 20,
    "name": "Gosht Dopiyaza",
    "category": "Main Courses - Lamb",
    "ingredients": [
      "Mutton ½ kg (small pieces)",
      "Tomatoes 2",
      "Green chilies 4 (coarsely chopped)",
      "Whole red chilies 6",
      "Oil ½ cup",
      "Onion 4 - 5 (coarsely chopped)",
      "Red chili 1 tsp heaped (crushed)",
      "Salt to taste",
      "Ginger 1 tsp (finely chopped)",
      "Garlic 1 tsp (finely chopped)",
      "White cumin whole 1 tsp",
      "Mixed whole spice 1 tbsp",
      "Turmeric ¼ tsp",
      "Coriander leaves 2 tbsp (chopped)",
      "Yogurt 4 tbsp",
      "Water 1/2 cup"
    ],
    "instructions": [
      "In a pan put together oil, mutton pieces, tomatoes, salt, green chilies, onions, and yogurt.",
      "Then add crushed red chili, ginger, garlic, white cumin seeds, whole red chilies, mixed whole spice and turmeric.",
      "Cook over low flame for 30 minutes.",
      "If required add water.",
      "When meat is tender, stir fry till oil forms a layer.",
      "Garnish with coriander leaves and serve."
    ]
  },
  {
    "id": 21,
    "name": "Mughlai Mutton Malai",
    "category": "Main Courses - Lamb",
    "ingredients": [
      "Mutton ½ kg",
      "Salt 1 tsp heaped",
      "Yogurt 1 cup",
      "Coriander powder 1½ tsp",
      "Garam masala powder 1 tsp leveled",
      "Lemon juice 2 tbsp",
      "Cumin 1 tsp heaped (roasted and crushed)",
      "Chili powder 1½ tsp",
      "Brown onion 3tbsp (crushed)",
      "Kewra water 1tbsp",
      "Saffron ¼tsp",
      "Ginger garlic paste 1tbsp",
      "Green cardamom powder ¼tsp",
      "Cashew nuts 1tbsp (ground)",
      "Malai 2tbsp",
      "Mint leaves 10",
      "Oil as required"
    ],
    "instructions": [
      "Marinate meat with salt, yogurt, coriander powder, garam masala powder, lemon juice, cumin, chili powder, brown onion, ginger garlic paste and green cardamom powder, leave to marinate for 1 hour.",
      "Heat oil add marinated mutton, cover and simmer on low flame for 30 minutes.",
      "Add in cashew nuts paste mixed with malai, kewra water, saffron and mint leaves.",
      "Leave it on simmer till oil floats on top.",
      "Serve with naan."
    ]
  },
  {
    "id": 22,
    "name": "Bori Curry",
    "category": "Main Courses - Lamb",
    "ingredients": [
      "Mutton 1 kg (boneless)",
      "Stock 1 cup",
      "Coriander 4 tbsp (whole)",
      "Green chili 8 – 10",
      "Coconut 2 tbsp",
      "chick pea powder ½ cup",
      "Tamarind paste ½ cup",
      "Potato 3",
      "Onion 3 (sliced)",
      "Turmeric ½ tsp (powder)",
      "Red chili 3 (whole)",
      "Green coriander ½ bunch",
      "Mint ½ bunch",
      "Clove 5",
      "Cinnamon stick 3",
      "Almond 10",
      "Peanuts 1 tbsp (roasted)",
      "Sesame 2 tbsp",
      "Curry leaves (2 stems)",
      "Oil 1 cup",
      "Salt to taste"
    ],
    "instructions": [
      "First heat pan and roast whole red chili, peanuts, chick pea powder, almond and sesame seeds.",
      "Now grind the roasted spices almond with onion, garlic, coconut, coriander, cumin and red chili with stock.",
      "Heat oil in a pan, add curry leaves, cinnamon stick and cloves, fry for a minute.",
      "Now add meat, turmeric, roasted and the ground paste and sautée for 3 – 4 minutes.",
      "Cook till meat tender, then put potato, tamarind paste, coconut and salt.",
      "When curry is prepared garnish it with coriander and mint and dish it out."
    ]
  },
  {
    "id": 23,
    "name": "Mutton Dry Fruit Curry",
    "category": "Main Courses - Lamb",
    "ingredients": [
      "Mutton 1/2 kg",
      "Apricot 1 cup",
      "Almond 2 tbsp",
      "Pistachio 2 tbsp",
      "Walnut 2 tbsp",
      "Raisin 2 tbsp",
      "Yogurt 1 1/2 cup",
      "White pepper powder 1/2 tsp",
      "Cinnamon stick 2 to 3",
      "Clove 3 to 4",
      "Onion (fried, crushed) 2",
      "Garlic (chopped) 1 tbsp",
      "Ginger (chopped) 2 tbsp",
      "Coriander powder 1 tsp",
      "Cumin powder 1/2 tsp",
      "Red chili crushed 1 tbsp",
      "Green chili chopped 4 to 5",
      "Tomato chopped 3",
      "Garammasala powder 1/4 tsp",
      "Cream 3 tbsp",
      "Clarified butter 1/2 cup",
      "Salt to taste"
    ],
    "instructions": [
      "First pour clarified butter into a pan.",
      "Now add cinnamon stick, clove, ginger garlic chopped and mutton into the pan and cook it on high flame from 4 to 5 minutes.",
      "Put brown onion into the pan.",
      "Pour yogurt into the pan and cook for a couple of minutes.",
      "Now add white pepper, coriander powder, cumin powder, red chili, garam masala and water, cook till mutton tenders.",
      "After that put tomato, green chili, salt and all dry fruit and cook it for 10 minute.",
      "In the end put cream from top and dish it out."
    ]
  },
  {
    "id": 24,
    "name": "Keri ka Dopiyaza",
    "category": "Main Courses - Lamb",
    "ingredients": [
      "Mutton ½ kg",
      "Coriander leaves 1 bunch (chopped)",
      "Oil 1 cup",
      "Raw mango 2",
      "Whole green chilies 4",
      "Curry leaves few",
      "Onion 750 gm",
      "Turmeric 1 tsp",
      "Chili powder 1 tbsp",
      "Ginger garlic paste 1 tbsp",
      "Salt to taste"
    ],
    "instructions": [
      "In a pan put together mutton, bunch of chopped coriander leaves and oil.",
      "Add raw mangoes, whole green chilies, few curry leaves, chopped onion, turmeric, chili powder, ginger garlic paste and salt to taste.",
      "Cook over low flame without adding water.",
      "Cook well till water dries.",
      "Garnish with coriander leaves and serve with plain boiled rice."
    ]
  },
  {
    "id": 25,
    "name": "Akhrot Aab Gosht",
    "category": "Main Courses - Lamb",
    "ingredients": [
      "Mutton chops 1 kg",
      "Roasted walnut ½ cup",
      "Onion 4",
      "Garlic 5 to 6",
      "Stock 2 cup",
      "Cinnamon stick 1 to 2",
      "Clove 2 to 3",
      "Milk 4 cup",
      "Cream 2 tbsp",
      "Aniseed 1 tbsp",
      "Cumin powder ½ tsp",
      "White pepper powder 1 tsp",
      "Cardamom 6 to 7",
      "Oil 4 tbsp",
      "Salt as required"
    ],
    "instructions": [
      "Take a pan, pour some water as you required and put chops and stock into the pan.",
      "Now add salt, cinnamon, clove, cardamom and brown onion and cook it well.",
      "Boil milk with cardamom, clove and sugar.",
      "When milk boiled, cool it down and add cream in it and pour it into the meat.",
      "When meat cooked, put it on a side.",
      "Now prepare a baghar.",
      "Now take a pan and add oil, aniseed powder, cumin powder, white pepper and when smell starting to come, pour it on meat and dish it out."
    ]
},
{
        "id": 26,
        "name": "Mutton with White Lentils and Eggs",
        "category": "Main Courses - Lamb",
        "ingredients": [
          "Mutton ¼ kg",
          "White lentils 1 cup",
          "Onion 1 (finely cut)",
          "Tomatoes 2 (finely cut)",
          "Red chili powder 1 tsp",
          "Hot spices powder 1 tsp",
          "Ginger 1 tbsp (finely cut)",
          "All spices 1 tbsp (whole)",
          "Turmeric powder ½ tsp",
          "Garlic 2 tsp (chopped)",
          "Oil ¼ cup",
          "Salt to taste",
          "Finely cut ginger 1 - for garnishing",
          "Boiled egg 2 - for garnishing",
          "Green chilies 1 tbsp - for garnishing",
          "Fresh coriander 2 tbsp - for garnishing"
        ],
        "instructions": [
          "Boil white lentils with turmeric, strain and set aside.",
          "Put mutton, onion, ginger, garlic, salt, red chili, all spices and water in a pot, cook till tender.",
          "Add oil and tomatoes, fry till oil separates.",
          "Add lentils, green chillies, ginger and little water, allow simmering.",
          "Garnish with ginger, boiled eggs, green chillies and fresh coriander.",
          "Serve hot."
        ]
      },
      {
        "id": 27,
        "name": "Pistachio Mutton",
        "category": "Main Courses - Lamb",
        "ingredients": [
          "Mutton 1 kg",
          "Cream 5 tbsp",
          "Yogurt 3 tbsp",
          "Garlic 5 to 6 cloves",
          "Cinnamon stick 2",
          "Tomato pulp 2",
          "Stock 3 cup",
          "Pistachio ½ cup",
          "Green chili 6 to 7",
          "Onion 2",
          "Ginger 1",
          "Garam masala powder ¾ tsp",
          "White pepper ¾ tsp",
          "Aniseed 1 tsp",
          "Cardamom powder 1 tsp",
          "Coriander 2 tbsp",
          "Oil 1 cup"
        ],
        "instructions": [
          "Boil all the pistachio and peel its skin.",
          "Now put pistachio, cream, green chili in a blender and make a paste and mix it in a yogurt.",
          "Pour oil in to a pan and fry onion till brown.",
          "Then add ginger garlic, garam masala powder, turmeric, cinnamon, white pepper and aniseed and cook it for 2 minutes.",
          "Then pour batter of pistachio and meat, stir well.",
          "After that add tomato, green chili, stock and salt in it and cook till meat tender.",
          "Garnish it with cardamom powder and green coriander."
        ]
      },
      {
        "id": 28,
        "name": "Handi Gola Kabab",
        "category": "Main Courses - Lamb",
        "ingredients": [
          "Mince ½ kg (double machined)",
          "Chickpeas 2 tbsp (grinded)",
          "Desiccated coconut 2 tbsp (roasted and grinded)",
          "Piper cubeba or kabab chini ½ tsp (grinded)",
          "Black cumin seed ½ tsp",
          "Brown onion 2 tbsp (heaped)",
          "Raw onion 1 (grated)",
          "Salt 1 tsp",
          "Chili powder 1 tsp (heaped)",
          "Ginger garlic paste 1 tbsp",
          "Garam masala powder 1 tsp",
          "Raw papaya 1 tsp",
          "Coriander powder ½ tsp (heaped)",
          "Cumin 1 tsp (roasted and crushed)",
          "Oil ½ cup"
        ],
        "instructions": [
          "Grind together chickpeas, coconut, piper cubeba and black cumin seeds in chopper.",
          "Add mince with brown onion, raw onion, salt, chili powder, ginger garlic paste, Garam masala powder, raw papaya, coriander powder and cumin chopperized well till smooth.",
          "Make equal size of kababs, give gola kabab shape, small and oblong.",
          "Heat oil in a handi, keep putting the kabab in handi, cover and cook on low flame for 15 minutes till done.",
          "Serve garnish with onion rings, tomato rings and mint leaves."
        ]
      },
      {
        "id": 29,
        "name": "Kandhari Gosht",
        "category": "Main Courses - Lamb",
        "ingredients": [
          "Mutton ½ kg",
          "Yogurt ½ cup",
          "Ginger garlic 1 tbsp (ground)",
          "Turmeric 1 tsp",
          "Salt to taste",
          "Clove 4",
          "Cinnamon 1 piece",
          "Green chili 4 (chopped)",
          "Oil ½ cup",
          "Pomegranate 2 – 3 (take out juice)",
          "Onion 3 (finely chopped)",
          "Red chili ½ tbsp (ground)",
          "Coriander 1 tbsp (ground)",
          "Whole all spice and black pepper 6",
          "Black cardamom 3",
          "Nutmeg mace ½ tsp (ground)",
          "Almond 20 (boiled, peeled)"
        ],
        "instructions": [
          "Soak mutton meat in pomegranate juice for 2 hours.",
          "Preheat oil in a pot and then add whole all spice and onion.",
          "When onion becomes golden brown then take out mutton meat from juice and put it in onion pot.",
          "When water dries up then add turmeric, chili, nutmag mace, coriander, ginger garlic paste and salt.",
          "Add water and tender the meat then beat yogurt and add it.",
          "Now add green chili and roast for five minutes and keep on simmer (dum).",
          "Before serving sprinkle almonds over dish.",
          "Delicious Kandhari mutton meat is ready to serve with naan."
        ]
      },
      {
        "id": 30,
        "name": "Mutton paneer",
        "category": "Main Courses - Lamb",
        "ingredients": [
          "Mutton 1 kg (boneless, small pieces)",
          "Paneer 200 gm (cut in to small cubes)",
          "Ginger garlic paste 1 tbsp",
          "Garam masala powder 1 tsp",
          "Red chili powder 1 tsp",
          "Clarified butter 1 cup",
          "Coriander powder 1 tbsp",
          "Whole white cumin 1 tsp (roast and ground)",
          "Rose water (kewra) few drops",
          "Capsicum 3 (cut into strips)",
          "Yogurt 1 cup",
          "Turmeric powder 1 tbsp",
          "Onion 1 cup (finely chopped)",
          "Green cardamom 6",
          "Salt to taste"
        ],
        "instructions": [
          "Heat oil in a pot and fry green cardamom for few minutes.",
          "Then add onion and fry till golden brown.",
          "Then add ginger garlic paste, coriander powder, red chili powder,garam masala ,salt, cumin, turmeric powder and mutton; roast for a while.",
          "Now combine yogurt in it and roast well.",
          "Add one cup hot water and cook until meat is tender.",
          "Once meat is tender then add capsicum and roast well.",
          "Finally add cottage cheese cubes and simmer on low heat for 5 minutes.",
          "Mutton cheese is ready to serve with boiled rice."
        ]
      },
      {
        "id": 31,
        "name": "Meat Kadhi",
        "category": "Main Courses - Lamb",
        "ingredients": [
          "Mutton 1 kg",
          "Tamarind juice 1 cup",
          "Oil 1 cup",
          "Tomatoes 2 chopped",
          "Onions 3 sliced",
          "Green chilies 4",
          "curry leaves 6 to 8",
          "Turmeric powder 1 tsp",
          "Poppy seeds 1 tbsp",
          "Ginger garlic paste 1 tbsp",
          "Red chili powder 1 tbsp",
          "White cumin ½ tbsp",
          "Rice 2 tbsp",
          "Coriander seeds 2 tbsp",
          "White sesame seeds 2 tbsp",
          "Salt to taste"
        ],
        "instructions": [
          "Soak rice and crush finely.",
          "In a cooking pot, add mutton, turmeric powder, red chili powder, ginger garlic paste, sliced onions, salt, oil and 2 cups water and allow cooking.",
          "Crush together sesame seeds, coriander seeds, white cumin and poppy seeds.",
          "When meat is tender, add crushed spices and tamarind juice.",
          "Add crushed rice and tomatoes, stir continuously with a wooden spoon until karhi is thick.",
          "Finally add curry leaves and green chilies and allow cooking on low flame.",
          "Serve Khatti Kadhi with plain rice."
        ]
      },
      {
        "id": 32,
        "name": "Beetroot Mutton",
        "category": "Main Courses - Lamb",
        "ingredients": [
          "Mutton ½ kg",
          "Oil ½ cup",
          "Onion 2 (sliced)",
          "Ginger garlic paste 1 tbsp",
          "Tomatoes 4 (finely chopped)",
          "Salt to taste",
          "Chili powder 2 tsp",
          "Turmeric ½ tsp",
          "Beetroots ½ kg (peeled and grated)",
          "Garam masala powder 1 tsp",
          "Lemon juice 1 tbsp",
          "Green chilies 3 (chopped)",
          "Coriander leaves 3 tbsp (chopped)"
        ],
        "instructions": [
          "Heat ½ cup oil add onion fry till light golden.",
          "Add ginger garlic paste with tomatoes, salt, chili powder, turmeric and mutton fry well.",
          "Add 1 ½ cup water, cover and cook till mutton half done.",
          "Then add beetroots with ½ cup water, cover and cook till beet root tender.",
          "Lastly add garam masala, lemon juice and green chilies, leave it on simmer.",
          "Garnish with coriander leaves and serve."
        ]
      },
      {
        "id": 33,
        "name": "Raan Musalam",
        "category": "Main Courses - Lamb",
        "ingredients": [
          "Mutton leg 1 ½ kg",
          "Ginger garlic paste 2 tbsp",
          "Raw papaya 4 tbsp (grinded)",
          "Chili powder 2 tsp",
          "Salt 1 ½ tsp heaped",
          "Turmeric 1 tsp",
          "Garam masala powder 1 tsp",
          "Oil 1 cup",
          "Onion 1 cup (chopped)",
          "Yogurt 1 cup",
          "Coriander seeds 1 tbsp (roasted and grinded)",
          "Cumin seeds 1 tsp (roasted and grinded)",
          "Coconut 1 tbsp (desiccated, roasted and grinded)",
          "Cashew nuts 8 (grinded)",
          "Nutmeg ¼ tsp (grinded)",
          "Mace ¼ tsp (grinded)",
          "Green cardamom ½ tsp (grinded)",
          "Kewra water 1 tbsp",
          "Saffron ½ tsp",
          "Cream 2 tbsp",
          "Coriander leaves 1 tbsp"
        ],
        "instructions": [
          "Prick mutton legs with fork and give deep cuts.",
          "Marinate the leg with ginger garlic paste, raw papaya, chili powder, salt, turmeric and garam masala.",
          "Rub spices very well on mutton leg.",
          "Leave to marinate overnight.",
          "Heat oil in a large wide pan, add onion and marinated legs, fry for 10 minutes till light golden.",
          "Add yogurt mixed with coriander, cumin, coconut, cashew nut, nutmeg, mace and green cardamom, fry well.",
          "Add 2 cups water, cover and cook for about 40 minutes.",
          "When mutton legs tender add kewra water mixed with saffron, cook till gravy thick.",
          "Transfer mutton legs to serving platter.",
          "Drizzle with cream, garnish with chopped coriander."
        ]
      },
      {
        "id": 34,
        "name": "Aloo Gosht",
        "category": "Main Courses - Lamb",
        "ingredients": [
          "Mutton ½ kg",
          "Potato 4",
          "Turmeric powder 1 ½ tsp",
          "Onion 2 (finely chopped)",
          "Red chili powder 1 tbsp",
          "Ginger garlic paste 1 tbsp",
          "Salt to taste",
          "Oil ½ cup",
          "Yogurt ½ cup",
          "Green chili 2",
          "Garam masala powder 1 tsp",
          "Fresh coriander leaves ½ bunch (chopped)",
          "Green chilies 2 (chopped)"
        ],
        "instructions": [
          "Peel potatoes and cut them into pieces.",
          "Mix ½ tsp turmeric powder with water and soak the potato pieces in it.",
          "In a pan heat oil, add mutton, onion, ginger garlic, 1 tsp turmeric powder, red chili powder, salt and 2 cups of hot water.",
          "Cook till water dries and meat tenders.",
          "Then add in yogurt and pieces of potatoes and stir fry.",
          "Now add 2 cup of water, cover and simmer for 10 minutes.",
          "When the oil separates, add in garam masala powder, fresh coriander leaves and chopped green chilies and keep it on a low flame.",
          "Serve it hot with naan."
        ]
      },
      {
        "id": 35,
        "name": "Mutton ball",
        "category": "Main Courses - Lamb",
        "ingredients": [
          "Potatoes ½ kg (boiled)",
          "Salt to taste",
          "Chili powder 1 tsp",
          "Oil 3 tbsp",
          "Fennel seeds ½ tsp (crushed)",
          "Onion 1 (chopped)",
          "Ginger 1 piece (chopped)",
          "Garlic clove 3 – 4 (chopped)",
          "Mutton mince ½ kg",
          "Tomato 2 (boiled, chopped)",
          "Water 1 cup",
          "Green chilies 2 – 3 (chopped)",
          "Coriander leaves 2 – 3 tbsp",
          "Egg 2",
          "Milk 2 tbsp",
          "Flour 3 – 4 tbsp",
          "Bread crumbs 1 cup",
          "Oil for fry",
          "Cumin powder 1 tsp - for spicy paste",
          "Coriander powder 1 tsp - for spicy paste",
          "Fennel seeds 1 tsp (ground) - for spicy paste",
          "Turmeric ½ tsp - for spicy paste",
          "Garam masala powder ½ tsp - for spicy paste",
          "Water 3 – 4 tbsp - for spicy paste"
        ],
        "instructions": [
          "In a bowl mix together cumin powder, coriander powder, fennel seeds, turmeric and garam masala powder.",
          "Add in 3 tbsp water and make into paste. Keep it aside.",
          "In a bowl mash potatoes very well.",
          "Add in a little salt and chili powder. Mix well and keep aside.",
          "Heat 3 tbsp oil in a pan, add fennel seeds and slightly fry.",
          "Now add onion, ginger and garlic clove.",
          "Fry well till garlic is golden brown.",
          "Now add mutton mince and fry till water dries.",
          "Add in prepared spices mixture and cook for 3 – 4 minutes.",
          "Add in tomatoes, also add 1 cup water and a little salt.",
          "Cover and cook for 4 – 5 minutes.",
          "Remove the lid, fry well till water dries.",
          "Then add green chilies, coriander leaves and mix well.",
          "Remove from fire, keep aside to cool.",
          "In a bowl beat together eggs and milk.",
          "Take a little mashed potato mixture in your hand, flatten a little, put some cooked mince, stuff and make into ball.",
          "Sprinkle each ball with a little flour, dip in beaten egg mixture and coat with bread crumbs.",
          "Now deep fry till golden brown and crisp."
        ]
      },
      {
        "id": 36,
        "name": "Karahi Tikka",
        "category": "Main Courses - Lamb",
        "ingredients": [
          "Meat ½ kg",
          "Carom seeds a pinch",
          "Oil 1 cup",
          "Yogurt 1 cup",
          "Coriander leaves few",
          "Green chilies 6 to 8",
          "Cumin seeds 1 tsp",
          "Garam masala powder 1 tsp",
          "Crushed red chili 1 tbsp",
          "Ginger garlic paste 2 tsp",
          "Salt to taste"
        ],
        "instructions": [
          "Cut meat in small cubes and marinate with salt, leave it for 2 hours.",
          "Heat oil in pan and fry marinated meat cubes till golden brown.",
          "Now add yogurt, a pinch of Carom seeds, cumin seeds, garam masala powder, crushed red chili and ginger garlic paste.",
          "Cook over low flame for 30 minutes till meat tender.",
          "Turn the flame off, garnish with Coriander leaves and green chilies.",
          "Serve hot."
        ]
      },
      {
        "id": 37,
        "name": "Fried Chops with Capsicum",
        "category": "Main Courses - Lamb",
        "ingredients": [
          "Chops ½ kg",
          "Yogurt 250 gm",
          "Salt to taste",
          "Black pepper powder 1 tsp",
          "White cumin seeds 1 tsp",
          "Garam masala powder 1 tsp",
          "Coriander powder 1 tsp",
          "Vinegar 3 tbsp",
          "Soya sauce 2 tbsp",
          "Oil 2 tbsp",
          "Oil ¼ cup",
          "Capsicum 1 (chopped)",
          "Onion 1",
          "Green chilies 3 – 4"
        ],
        "instructions": [
          "In a bowl mix together yogurt, salt, black pepper, cumin seeds, garam masala powder, coriander powder, vinegar, soya sauce and 2 tbsp oil.",
          "Marinate chop with the mixture and keep aside for 10 – 15 minutes.",
          "Now put marinated chops in a pan with its marinade.",
          "Cook till water dries and chops are tender.",
          "In another pan heat oil.",
          "Add capsicum, onion and green chilies. Sauté a little.",
          "Now add chops and cook for a few seconds.",
          "Remove from fire.",
          "Dish it out and serve hot."
        ]
      },
      {
        "id": 38,
        "name": "Namkeen Gosht",
        "category": "Main Courses - Lamb",
        "ingredients": [
          "Mutton meat with bone 1 kg",
          "Garlic cloves 10 (chopped)",
          "Ginger 1 tsp (fine slice)",
          "Onion 1",
          "Whole black pepper 1 tsp (crushed)",
          "Coriander seed 1 tsp (roasted and crushed)",
          "Cumin seeds 1 tsp (crushed)",
          "Turmeric powder ½ tsp",
          "Salt to taste",
          "Oil 2 tbsp",
          "Water as required"
        ],
        "instructions": [
          "Take meat with fat & bone on it.",
          "Take medium size cooking pot, put on the fire, put oil, as the oil get warm, put chopped onion, garlic cloves crushed, slice ginger, stir it for couple of minutes.",
          "Put meat into the pot stir it for couple on minutes.",
          "Add crushed black pepper, roasted coriander seed crushed, cumin seeds crushed, turmeric powder and salt, stir it for some minutes.",
          "Add water till the ingredients are dip into the water, let it cook at medium flame till the water is dried & the meat is cooked to tender.",
          "Serve with chapatti or naan."
        ]
      },
      {
        "id": 39,
        "name": "Phal Chops",
        "category": "Main Courses - Lamb",
        "ingredients": [
          "Chops ½ kg",
          "Onion 2 (medium, sliced)",
          "Coriander leaves ½ cup",
          "Green chilies 8",
          "Ginger garlic paste 1 tbsp",
          "Black pepper 1 tbsp (whole)",
          "Yogurt 1 cup",
          "Lemon juice 2 tbsp",
          "Salt 1 tsp heaped",
          "Oil ¼ cup"
        ],
        "instructions": [
          "Blend together onion, coriander leaves, green chilies, ginger garlic paste, black pepper, yogurt, lemon juice and salt.",
          "Marinate chops with this half mixture for 2 hours.",
          "Heat oil fry remaining mixture for 5 minutes till slightly brown.",
          "Add in the chops, fry well.",
          "Add 1 cup water, cover and leave it to cook until chops tender."
        ]
      },
      {
        "id": 40,
        "name": "Roasted Chops",
        "category": "Main Courses - Lamb",
        "ingredients": [
          "Chops 1 kg",
          "Ginger garlic paste 2 tsp",
          "Papaya paste/meat tenderizer 2 tbsp",
          "Salt to taste",
          "Red chili powder 1 tsp",
          "Hot spice powder 1 tsp",
          "Cumin powder ½ tsp",
          "Yogurt 2 tbsp",
          "Oil as required"
        ],
        "instructions": [
          "Mix ginger garlic paste, papaya paste/meat tenderizer, salt, red chili powder, hot spice powder, cumin powder and yogurt.",
          "Rub mixture on chops and leave for marination about 2 hours.",
          "Preheat over at 180 degree C. grease baking tray and place chops on tray. Drizzle oil on chops.",
          "Cook about 30 minutes or until meat tender. Turn chops in the half way so they brown from both sides.",
          "Serve with dip."
        ]
      }
    ]
  }